{
  "type": "minecraft:crafting_shapeless",
  "group": "burrito",
  "ingredients": [
    {
      "item": "wildnature:tortilla"
    },
    {
      "item": "minecraft:cooked_chicken"
    },
    {
      "item": "wildnature:lettuce"
    },
    {
      "item": "wildnature:lettuce"
    },
    {
      "item": "wildnature:lettuce"
    },
    {
      "item": "wildnature:corn"
    },
    {
      "item": "wildnature:corn"
    },
    {
      "item": "wildnature:cheddar_cheese"
    }
  ],
  "result": {
    "item": "wildnature:chicken_and_corn_burrito",
    "count": 1
  }
}